{
    "content": [
        {
            "N": 0,
            "action": "read-catalog",
            "timestamp": "15.02.2021, 23:44:10"
        },
        {
            "N": 1,
            "action": "read-cart",
            "timestamp": "15.02.2021, 23:44:10"
        },
        {
            "N": 2,
            "action": "add-new-product",
            "id": 456,
            "title": "Мышка",
            "price": 1000,
            "quantity": 3,
            "amount": 3000,
            "timestamp": "15.02.2021, 23:44:14"
        },
        {
            "N": 3,
            "action": "change-product",
            "id": 456,
            "title": "Мышка",
            "price": 1000,
            "quantity": 4,
            "amount": 4000,
            "timestamp": "15.02.2021, 23:44:20"
        },
        {
            "N": 4,
            "action": "change-product",
            "id": 456,
            "title": "Мышка",
            "price": 1000,
            "quantity": 5,
            "amount": 5000,
            "timestamp": "15.02.2021, 23:44:21"
        },
        {
            "N": 5,
            "action": "change-product",
            "id": 456,
            "title": "Мышка",
            "price": 1000,
            "quantity": 4,
            "amount": 4000,
            "timestamp": "15.02.2021, 23:44:22"
        },
        {
            "N": 6,
            "action": "change-product",
            "id": 456,
            "title": "Мышка",
            "price": 1000,
            "quantity": 3,
            "amount": 3000,
            "timestamp": "15.02.2021, 23:44:22"
        },
        {
            "N": 7,
            "action": "change-product",
            "id": 456,
            "title": "Мышка",
            "price": 1000,
            "quantity": 2,
            "amount": 2000,
            "timestamp": "15.02.2021, 23:44:22"
        },
        {
            "N": 8,
            "action": "change-product",
            "id": 456,
            "title": "Мышка",
            "price": 1000,
            "quantity": 1,
            "amount": 1000,
            "timestamp": "15.02.2021, 23:44:23"
        },
        {
            "N": 9,
            "action": "delete-product",
            "id": 456,
            "title": "Мышка",
            "price": 1000,
            "quantity": 1,
            "amount": 1000,
            "timestamp": "15.02.2021, 23:44:25"
        },
        {
            "N": 10,
            "action": "add-new-product",
            "id": 124,
            "title": "Клавиатура",
            "price": 1600,
            "quantity": 1,
            "amount": 1600,
            "timestamp": "15.02.2021, 23:44:28"
        },
        {
            "N": 11,
            "action": "read-catalog",
            "timestamp": "15.02.2021, 23:44:31"
        },
        {
            "N": 12,
            "action": "read-cart",
            "timestamp": "15.02.2021, 23:44:31"
        },
        {
            "N": 13,
            "action": "delete-product",
            "id": 124,
            "title": "Клавиатура",
            "price": 1600,
            "quantity": 1,
            "amount": 1600,
            "timestamp": "15.02.2021, 23:44:40"
        },
        {
            "N": 14,
            "action": "read-catalog",
            "timestamp": "15.02.2021, 23:44:42"
        },
        {
            "N": 15,
            "action": "read-cart",
            "timestamp": "15.02.2021, 23:44:42"
        }
    ],
    "_id": 16
}